v2share/__init__.py
v2share/_utils.py
v2share/_version.py
v2share/base.py
v2share/clash.py
v2share/clashmeta.py
v2share/data.py
v2share/exceptions.py
v2share/links.py
v2share/singbox.py
v2share/wireguard.py
v2share/xray.py
v2share/templates/clash.yml
v2share/templates/singbox.json
v2share/templates/xray.json
v2share/templates/xray_mux.json
v2share-0.1.0b31.dist-info/METADATA
v2share-0.1.0b31.dist-info/WHEEL
v2share-0.1.0b31.dist-info/RECORD
