Metadata-Version: 2.4
Name: v2share
Version: 0.1.0b31
Summary: generate configurations painlessly for xray/sing-box/clash
Project-URL: Homepage, https://github.com/khodedawsh/v2share
Project-URL: Repository, https://github.com/khodedawsh/v2share.git
Project-URL: Issues, https://github.com/khodedawsh/v2share/issues
Author-email: Dawsh <dawsh@duck.com>
Maintainer-email: Dawsh <dawsh@duck.com>
Keywords: clash,proxy,sing-box,v2ray,vpn,xray,xray-core
Requires-Python: >=3.9
Requires-Dist: pyyaml>=6.0.1
